{
  "name": "Malaga",
  "state_name": "Spain",
  "required_documents": [
    "Passport", "CI"
  ],
  "internet_roaming": "Available",
  "daily_average_cost": 45,
  "description": "Malaga is places in the south of Spain, on the Mediterranean sea. Hot, with beautiful beaches, lively and very nice to visit. From the castle you can see an amazing vew of the city",
  "tags": [
    "nature", "beach", "sea", "church", "castle"
  ],
  "how_to_arrive": [
    "Airplane", "Bus", "Train", "Car"
  ],
  "how_to_move": [
    "Bike", "Walk", "Taxi", "Public transports"
  ],
  "resources": [
    "https://www.viviandalucia.com/malaga/10-cose-vedere-malaga/"
  ],
  "coworking": [
    "https://www.surfoffice.com/coworking/malaga", "https://www.regus.com/it-it/spain/malaga/coworking", "https://innovationcampus.biz/malaga/malaga-terrace/"
  ]
}
