{
  "name": "C14",
  "repository_platform": "github",
  "repository_url": "https://github.com/kkratterf/C14",
  "site_url": "https://www.c14.so",
  "type": "tool",
  "description": "A growing, open-source database of Italian startups \ud83c\uddee\ud83c\uddf9 Designed to make the ecosystem more transparent and accessible",
  "license": "AGPL-3.0",
  "tags": [
    "typescript",
    "react",
    "nextjs"
  ],
  "autogenerated": {
    "filename": "c14.json",
    "timestamp": "2025-10-13T08:22:06Z",
    "meta": {
      "name": "C14",
      "full_name": "kkratterf/C14",
      "html_url": "https://github.com/kkratterf/C14",
      "created_at": "2024-12-22T15:01:18Z",
      "updated_at": "2025-08-01T13:24:35Z",
      "pushed_at": "2025-10-06T20:05:07Z",
      "archived": false,
      "disabled": false,
      "owner": "kkratterf",
      "owner_type": "User",
      "topics": [
        "c14",
        "design-system",
        "nextjs",
        "open-source",
        "prisma",
        "supabase",
        "tailwindcss",
        "typescript",
        "vercel"
      ],
      "license": "GNU Affero General Public License v3.0"
    },
    "analytics": {
      "language": "TypeScript",
      "languages": {
        "TypeScript": 84.4,
        "MDX": 14.31,
        "CSS": 1.26,
        "JavaScript": 0.03
      },
      "languages_byte": {
        "TypeScript": 2295533,
        "MDX": 389227,
        "CSS": 34271,
        "JavaScript": 803
      },
      "stargazers_count": 11,
      "forks_count": 1,
      "open_issues_count": 1,
      "forks": 1,
      "open_issues": 1,
      "watchers": 11,
      "updated_at": "2025-10-13T08:22:06Z"
    }
  }
}