{
  "name": "Middy",
  "type": "package",
  "tags": [
    "nodejs",
    "javascript",
    "serverless",
    "aws lambda"
  ],
  "description": "The stylish Node.js middleware engine for AWS Lambda",
  "site_url": "https://middy.js.org",
  "repository_platform": "github",
  "repository_url": "https://github.com/middyjs/middy",
  "license": "MIT",
  "autogenerated": {
    "filename": "middy.json",
    "meta": {
      "name": "middy",
      "full_name": "middyjs/middy",
      "html_url": "https://github.com/middyjs/middy",
      "created_at": "2017-08-03T14:59:07Z",
      "updated_at": "2026-06-14T14:49:28Z",
      "pushed_at": "2026-06-12T19:52:34Z",
      "archived": false,
      "disabled": false,
      "owner": "middyjs",
      "owner_type": "Organization",
      "topics": [
        "aws",
        "aws-lambda",
        "aws-powertools",
        "aws-serverless",
        "framework",
        "javascript",
        "lambda",
        "lambda-handler",
        "middleware",
        "middy",
        "node",
        "nodejs",
        "powertools",
        "serverless",
        "serverless-applications",
        "serverless-express",
        "serverless-framework",
        "typescript"
      ],
      "license": "MIT License"
    },
    "analytics": {
      "language": "JavaScript",
      "languages": {
        "JavaScript": 91.97,
        "TypeScript": 5.61,
        "Svelte": 1.85,
        "CSS": 0.37,
        "Shell": 0.13,
        "HTML": 0.07
      },
      "languages_byte": {
        "JavaScript": 1780732,
        "TypeScript": 108657,
        "Svelte": 35866,
        "CSS": 7193,
        "Shell": 2535,
        "HTML": 1288
      },
      "stargazers_count": 3900,
      "forks_count": 399,
      "open_issues_count": 6,
      "forks": 399,
      "open_issues": 6,
      "watchers": 3900,
      "updated_at": "2026-06-15T15:13:03Z"
    },
    "timestamp": "2026-06-15T15:13:03Z"
  }
}